minium_mcp_server/__init__.py
minium_mcp_server/server.py
minium_mcp_server-0.1.1.dist-info/METADATA
minium_mcp_server-0.1.1.dist-info/WHEEL
minium_mcp_server-0.1.1.dist-info/entry_points.txt
minium_mcp_server-0.1.1.dist-info/RECORD
