Metadata-Version: 2.4
Name: minium-mcp-server
Version: 0.1.1
Summary: A MCP server project
Author: roy.yan
Requires-Python: >=3.12
Requires-Dist: argparse>=1.4.0
Requires-Dist: asyncio>=3.4.3
Requires-Dist: mcp>=1.4.1
Requires-Dist: minium
